uvenv/__init__.py
uvenv/__version__.py
uvenv/_constants.py
uvenv/cli.py
uvenv/execute.py
uvenv/project.py
uvenv/uv.py
uvenv_cli-0.1.1.dist-info/LICENSE
uvenv_cli-0.1.1.dist-info/METADATA
uvenv_cli-0.1.1.dist-info/WHEEL
uvenv_cli-0.1.1.dist-info/entry_points.txt
uvenv_cli-0.1.1.dist-info/top_level.txt
uvenv_cli-0.1.1.dist-info/RECORD
