Metadata-Version: 2.1
Name: uvenv-cli
Version: 0.1.1
Summary: A virtual environment manager for Python.
Home-page: https://github.com/kennethreitz/uvenv
Author: Kenneth Reitz
Author-email: me@kennethreitz.org
License: MIT
Classifier: License :: OSI Approved :: MIT License
Classifier: Programming Language :: Python
Classifier: Programming Language :: Python :: 3
Classifier: Programming Language :: Python :: 3.10
Classifier: Programming Language :: Python :: 3.11
Classifier: Programming Language :: Python :: 3.12
Classifier: Programming Language :: Python :: 3.13
Classifier: Programming Language :: Python :: Implementation :: CPython
Classifier: Programming Language :: Python :: Implementation :: PyPy
Requires-Python: >=3.6.0
License-File: LICENSE
Requires-Dist: docopt
Requires-Dist: delegator
Requires-Dist: uv
